{"paging":{"pageIndex":1,"pageSize":500,"total":16},"baseComponent":{"id":"AX8pS7ARvLjR4aiZ_EHh","key":"fga-eps-mds_2021.2-Eu-Pescador-FishLog","name":"2021.2-Eu-Pescador-FishLog","qualifier":"TRK","measures":[{"metric":"duplicated_lines_density","value":"0.0","bestValue":true},{"metric":"functions","value":"20"},{"metric":"test_execution_time","value":"122"},{"metric":"test_failures","value":"0","bestValue":true},{"metric":"test_errors","value":"0","bestValue":true},{"metric":"security_rating","value":"1.0","bestValue":true},{"metric":"tests","value":"23"},{"metric":"files","value":"8"},{"metric":"complexity","value":"46"},{"metric":"ncloc","value":"384"},{"metric":"coverage","value":"77.1","bestValue":false},{"metric":"comment_lines_density","value":"0.3","bestValue":false}]},"components":[{"id":"AX8piVlbvVqm2CoaIRzu","key":"fga-eps-mds_2021.2-Eu-Pescador-FishLog:src/app.ts","name":"app.ts","qualifier":"FIL","path":"src/app.ts","language":"ts","measures":[{"metric":"coverage","value":"0.0","bestValue":false},{"metric":"complexity","value":"0"},{"metric":"functions","value":"0"},{"metric":"security_rating","value":"1.0","bestValue":true},{"metric":"comment_lines_density","value":"0.0","bestValue":false},{"metric":"ncloc","value":"11"},{"metric":"files","value":"1"},{"metric":"test_errors","value":"0","bestValue":true},{"metric":"duplicated_lines_density","value":"0.0","bestValue":true},{"metric":"test_failures","value":"0","bestValue":true}]},{"id":"AX8piVlbvVqm2CoaIRzv","key":"fga-eps-mds_2021.2-Eu-Pescador-FishLog:src/middleware/auth.ts","name":"auth.ts","qualifier":"FIL","path":"src/middleware/auth.ts","language":"ts","measures":[{"metric":"complexity","value":"5"},{"metric":"functions","value":"3"},{"metric":"ncloc","value":"31"},{"metric":"coverage","value":"38.9","bestValue":false},{"metric":"security_rating","value":"1.0","bestValue":true},{"metric":"comment_lines_density","value":"0.0","bestValue":false},{"metric":"files","value":"1"},{"metric":"test_errors","value":"0","bestValue":true},{"metric":"duplicated_lines_density","value":"0.0","bestValue":true},{"metric":"test_failures","value":"0","bestValue":true}]},{"id":"AX8piVlbvVqm2CoaIRzt","key":"fga-eps-mds_2021.2-Eu-Pescador-FishLog:src/config","name":"config","qualifier":"DIR","path":"src/config","measures":[{"metric":"duplicated_lines_density","value":"0.0","bestValue":true},{"metric":"functions","value":"2"},{"metric":"security_rating","value":"1.0","bestValue":true},{"metric":"files","value":"1"},{"metric":"complexity","value":"4"},{"metric":"ncloc","value":"27"},{"metric":"coverage","value":"0.0","bestValue":false},{"metric":"comment_lines_density","value":"0.0","bestValue":false}]},{"id":"AX8piVlbvVqm2CoaIRz0","key":"fga-eps-mds_2021.2-Eu-Pescador-FishLog:src/controllers","name":"controllers","qualifier":"DIR","path":"src/controllers","measures":[{"metric":"duplicated_lines_density","value":"0.0","bestValue":true},{"metric":"functions","value":"8"},{"metric":"security_rating","value":"1.0","bestValue":true},{"metric":"files","value":"1"},{"metric":"complexity","value":"29"},{"metric":"ncloc","value":"186"},{"metric":"coverage","value":"84.7","bestValue":false},{"metric":"comment_lines_density","value":"0.0","bestValue":false}]},{"id":"AX8piVlbvVqm2CoaIRzs","key":"fga-eps-mds_2021.2-Eu-Pescador-FishLog:src/config/database.ts","name":"database.ts","qualifier":"FIL","path":"src/config/database.ts","language":"ts","measures":[{"metric":"complexity","value":"4"},{"metric":"functions","value":"2"},{"metric":"ncloc","value":"27"},{"metric":"coverage","value":"0.0","bestValue":false},{"metric":"security_rating","value":"1.0","bestValue":true},{"metric":"comment_lines_density","value":"0.0","bestValue":false},{"metric":"files","value":"1"},{"metric":"test_errors","value":"0","bestValue":true},{"metric":"duplicated_lines_density","value":"0.0","bestValue":true},{"metric":"test_failures","value":"0","bestValue":true}]},{"id":"AX8piVlbvVqm2CoaIRzx","key":"fga-eps-mds_2021.2-Eu-Pescador-FishLog:src/models/fishLog.ts","name":"fishLog.ts","qualifier":"FIL","path":"src/models/fishLog.ts","language":"ts","measures":[{"metric":"coverage","value":"100.0","bestValue":true},{"metric":"complexity","value":"0"},{"metric":"functions","value":"0"},{"metric":"security_rating","value":"1.0","bestValue":true},{"metric":"comment_lines_density","value":"0.0","bestValue":false},{"metric":"ncloc","value":"94"},{"metric":"files","value":"1"},{"metric":"test_errors","value":"0","bestValue":true},{"metric":"duplicated_lines_density","value":"0.0","bestValue":true},{"metric":"test_failures","value":"0","bestValue":true}]},{"id":"AX8piVlbvVqm2CoaIRz2","key":"fga-eps-mds_2021.2-Eu-Pescador-FishLog:test/controller/fishLogController.spec.ts","name":"fishLogController.spec.ts","qualifier":"UTS","path":"test/controller/fishLogController.spec.ts","language":"ts","measures":[{"metric":"test_execution_time","value":"122"},{"metric":"tests","value":"23"},{"metric":"security_rating","value":"1.0","bestValue":true},{"metric":"test_errors","value":"0","bestValue":true},{"metric":"duplicated_lines_density","value":"0.0","bestValue":true},{"metric":"test_failures","value":"0","bestValue":true}]},{"id":"AX8piVlbvVqm2CoaIRzz","key":"fga-eps-mds_2021.2-Eu-Pescador-FishLog:src/controllers/fishLogController.ts","name":"fishLogController.ts","qualifier":"FIL","path":"src/controllers/fishLogController.ts","language":"ts","measures":[{"metric":"complexity","value":"29"},{"metric":"functions","value":"8"},{"metric":"ncloc","value":"186"},{"metric":"coverage","value":"84.7","bestValue":false},{"metric":"security_rating","value":"1.0","bestValue":true},{"metric":"comment_lines_density","value":"0.0","bestValue":false},{"metric":"files","value":"1"},{"metric":"test_errors","value":"0","bestValue":true},{"metric":"duplicated_lines_density","value":"0.0","bestValue":true},{"metric":"test_failures","value":"0","bestValue":true}]},{"id":"AX8piVlbvVqm2CoaIRzq","key":"fga-eps-mds_2021.2-Eu-Pescador-FishLog:src/routes/fishLogRoutes.ts","name":"fishLogRoutes.ts","qualifier":"FIL","path":"src/routes/fishLogRoutes.ts","language":"ts","measures":[{"metric":"coverage","value":"0.0","bestValue":false},{"metric":"complexity","value":"6"},{"metric":"functions","value":"6"},{"metric":"security_rating","value":"1.0","bestValue":true},{"metric":"comment_lines_density","value":"0.0","bestValue":false},{"metric":"ncloc","value":"25"},{"metric":"files","value":"1"},{"metric":"test_errors","value":"0","bestValue":true},{"metric":"duplicated_lines_density","value":"0.0","bestValue":true},{"metric":"test_failures","value":"0","bestValue":true}]},{"id":"AX8piVlbvVqm2CoaIRzw","key":"fga-eps-mds_2021.2-Eu-Pescador-FishLog:src/middleware","name":"middleware","qualifier":"DIR","path":"src/middleware","measures":[{"metric":"duplicated_lines_density","value":"0.0","bestValue":true},{"metric":"functions","value":"3"},{"metric":"security_rating","value":"1.0","bestValue":true},{"metric":"files","value":"1"},{"metric":"complexity","value":"5"},{"metric":"ncloc","value":"31"},{"metric":"coverage","value":"38.9","bestValue":false},{"metric":"comment_lines_density","value":"0.0","bestValue":false}]},{"id":"AX8piVlbvVqm2CoaIRzy","key":"fga-eps-mds_2021.2-Eu-Pescador-FishLog:src/models","name":"models","qualifier":"DIR","path":"src/models","measures":[{"metric":"duplicated_lines_density","value":"0.0","bestValue":true},{"metric":"functions","value":"0"},{"metric":"security_rating","value":"1.0","bestValue":true},{"metric":"files","value":"1"},{"metric":"complexity","value":"0"},{"metric":"ncloc","value":"94"},{"metric":"coverage","value":"100.0","bestValue":true},{"metric":"comment_lines_density","value":"0.0","bestValue":false}]},{"id":"AX8piVlbvVqm2CoaIRzp","key":"fga-eps-mds_2021.2-Eu-Pescador-FishLog:src/routes/router.ts","name":"router.ts","qualifier":"FIL","path":"src/routes/router.ts","language":"ts","measures":[{"metric":"coverage","value":"0.0","bestValue":false},{"metric":"complexity","value":"0"},{"metric":"functions","value":"0"},{"metric":"security_rating","value":"1.0","bestValue":true},{"metric":"comment_lines_density","value":"16.7","bestValue":false},{"metric":"ncloc","value":"5"},{"metric":"files","value":"1"},{"metric":"test_errors","value":"0","bestValue":true},{"metric":"duplicated_lines_density","value":"0.0","bestValue":true},{"metric":"test_failures","value":"0","bestValue":true}]},{"id":"AX8piVlbvVqm2CoaIRzr","key":"fga-eps-mds_2021.2-Eu-Pescador-FishLog:src/routes","name":"routes","qualifier":"DIR","path":"src/routes","measures":[{"metric":"duplicated_lines_density","value":"0.0","bestValue":true},{"metric":"functions","value":"6"},{"metric":"security_rating","value":"1.0","bestValue":true},{"metric":"files","value":"2"},{"metric":"complexity","value":"6"},{"metric":"ncloc","value":"30"},{"metric":"coverage","value":"0.0","bestValue":false},{"metric":"comment_lines_density","value":"3.2","bestValue":false}]},{"id":"AX8piVlbvVqm2CoaIRzo","key":"fga-eps-mds_2021.2-Eu-Pescador-FishLog:src/server.ts","name":"server.ts","qualifier":"FIL","path":"src/server.ts","language":"ts","measures":[{"metric":"complexity","value":"2"},{"metric":"functions","value":"1"},{"metric":"ncloc","value":"5"},{"metric":"coverage","value":"0.0","bestValue":false},{"metric":"security_rating","value":"1.0","bestValue":true},{"metric":"comment_lines_density","value":"0.0","bestValue":false},{"metric":"files","value":"1"},{"metric":"test_errors","value":"0","bestValue":true},{"metric":"duplicated_lines_density","value":"0.0","bestValue":true},{"metric":"test_failures","value":"0","bestValue":true}]},{"id":"AX8piVlbvVqm2CoaIRz1","key":"fga-eps-mds_2021.2-Eu-Pescador-FishLog:src","name":"src","qualifier":"DIR","path":"src","measures":[{"metric":"duplicated_lines_density","value":"0.0","bestValue":true},{"metric":"functions","value":"20"},{"metric":"security_rating","value":"1.0","bestValue":true},{"metric":"files","value":"8"},{"metric":"complexity","value":"46"},{"metric":"ncloc","value":"384"},{"metric":"coverage","value":"77.1","bestValue":false},{"metric":"comment_lines_density","value":"0.3","bestValue":false}]},{"id":"AX8piVlbvVqm2CoaIRz3","key":"fga-eps-mds_2021.2-Eu-Pescador-FishLog:test/controller","name":"test/controller","qualifier":"DIR","path":"test/controller","measures":[{"metric":"test_execution_time","value":"122"},{"metric":"test_failures","value":"0","bestValue":true},{"metric":"test_errors","value":"0","bestValue":true},{"metric":"security_rating","value":"1.0","bestValue":true},{"metric":"tests","value":"23"}]}]}